{
  "display": {
    "icon": {
      "id": "minecraft:furnace",
      "components": {
        "minecraft:item_model": "simplenergy:simple_battery"
      }
    },
    "title": {
      "translate": "simplenergy.a_simple_energy_storage",
      "color": "gray"
    },
    "description": {
      "translate": "simplenergy.craft_your_first_simple_battery",
      "color": "green"
    },
    "frame": "task",
    "show_toast": true,
    "announce_to_chat": true,
    "hidden": false
  },
  "criteria": {
    "requirement": {
      "trigger": "minecraft:inventory_changed",
      "conditions": {
        "items": [
          {
            "predicates": {
              "minecraft:custom_data": {
                "simplenergy": {
                  "simple_battery": true
                }
              }
            }
          }
        ]
      }
    }
  },
  "requirements": [
    [
      "requirement"
    ]
  ],
  "parent": "simplenergy:visible/simplunium_ingot"
}
