{
	"type": "minecraft:notice",
	"title": [
		{
			"sprite": "simplenergy:item/simplunium_ingot",
			"shadow_color": [
				0,
				0,
				0,
				0
			],
			"atlas": "minecraft:items"
		},
		" ",
		{
			"translate": "simplenergy.simplunium_ingot",
			"underlined": true
		},
		" ",
		{
			"sprite": "simplenergy:item/simplunium_ingot",
			"shadow_color": [
				0,
				0,
				0,
				0
			],
			"atlas": "minecraft:items"
		}
	],
	"body": [
		{
			"type": "minecraft:plain_message",
			"contents": [
				{"text": "V   ","font": "simplenergy:manual","color": "white"},
				{"text": "\n   ","click_event": {"action": "show_dialog","dialog": "simplenergy:manual/page_7"},"hover_event": {"action": "show_text","value": [{"translate": "simplenergy.go_to_previous_page"}," (7)"]}},
				" ",
				{"text": "   ","click_event": {"action": "show_dialog","dialog": "simplenergy:manual/page_9"},"hover_event": {"action": "show_text","value": [{"translate": "simplenergy.go_to_next_page"}," (9)"]}},
				{"text": "\n   ","click_event": {"action": "show_dialog","dialog": "simplenergy:manual/page_7"},"hover_event": {"action": "show_text","value": [{"translate": "simplenergy.go_to_previous_page"}," (7)"]}},
				" ",
				{"text": "   ","click_event": {"action": "show_dialog","dialog": "simplenergy:manual/page_9"},"hover_event": {"action": "show_text","value": [{"translate": "simplenergy.go_to_next_page"}," (9)"]}}
			],
			"width": 400
		},
		{
			"type": "minecraft:plain_message",
			"contents": [
				{"text": "","font": "simplenergy:manual","color": "white","shadow_color": [0,0,0,0]},
				"\"$5\n\"",
				{"text": "$×Ç®","hover_event": {"action": "show_item","id": "furnace","components": {"custom_data": {"smithed": {"dict": {"block": {"simplunium": true}},"ignore": {"functionality": true,"crafting": true}},"simplenergy": {"simplunium_block": true}},"item_model": "simplenergy:simplunium_block","item_name": {"translate": "simplenergy.simplunium_block"},"lore": [["",{"text": "I","color": "white","italic": false,"font": "simplenergy:icons"},{"translate": "simplenergy","italic": true,"color": "blue"}]],"container": [{"slot": 0,"item": {"id": "minecraft:stone","count": 1,"components": {"minecraft:custom_data": {"smithed": {"block": {"id": "simplenergy:simplunium_block","from": "simplenergy"}}}}}}],"tooltip_display": {"hidden_components": ["minecraft:container"]}}},"click_event": {"action": "show_dialog","dialog": "simplenergy:manual/page_12"}},
				"U$  \n\"",
				{"text": "U$","hover_event": {"action": "show_item","id": "furnace","components": {"custom_data": {"smithed": {"dict": {"block": {"simplunium": true}},"ignore": {"functionality": true,"crafting": true}},"simplenergy": {"simplunium_block": true}},"item_model": "simplenergy:simplunium_block","item_name": {"translate": "simplenergy.simplunium_block"},"lore": [["",{"text": "I","color": "white","italic": false,"font": "simplenergy:icons"},{"translate": "simplenergy","italic": true,"color": "blue"}]],"container": [{"slot": 0,"item": {"id": "minecraft:stone","count": 1,"components": {"minecraft:custom_data": {"smithed": {"block": {"id": "simplenergy:simplunium_block","from": "simplenergy"}}}}}}],"tooltip_display": {"hidden_components": ["minecraft:container"]}}},"click_event": {"action": "show_dialog","dialog": "simplenergy:manual/page_12"}},
				"U$U$",
				{"text": "$$×éÅ","hover_event": {"action": "show_item","id": "command_block","components": {"custom_data": {"smithed": {"dict": {"ingot": {"simplunium": true}},"ignore": {"functionality": true,"crafting": true}},"simplenergy": {"simplunium_ingot": true}},"item_model": "simplenergy:simplunium_ingot","item_name": {"translate": "simplenergy.simplunium_ingot"},"lore": [["",{"text": "I","color": "white","italic": false,"font": "simplenergy:icons"},{"translate": "simplenergy","italic": true,"color": "blue"}]]}}},
				"#$\n\"U$U$U$",
				{"text": "U$","hover_event": {"action": "show_item","id": "command_block","components": {"custom_data": {"smithed": {"dict": {"ingot": {"simplunium": true}},"ignore": {"functionality": true,"crafting": true}},"simplenergy": {"simplunium_ingot": true}},"item_model": "simplenergy:simplunium_ingot","item_name": {"translate": "simplenergy.simplunium_ingot"},"lore": [["",{"text": "I","color": "white","italic": false,"font": "simplenergy:icons"},{"translate": "simplenergy","italic": true,"color": "blue"}]]}}},
				"#$\n\n\n",
				{"text": "2##","hover_event": {"action": "show_text","value": [{"text": ""},[{"text": "","font": "simplenergy:manual","color": "white"},"\"E\n","\"",{"text": "$×Ç®"},"\n","\"",{"text": "U$"},"U$U$",{"text": "$$×éÅ"},"\n\"","U$U$U$",{"text": "U$"},"\n","\n"],{"text": "\n- x1 ","color": "gray"},{"translate": "simplenergy.simplunium_block","color": "gray"}]},"click_event": {"action": "show_dialog","dialog": "simplenergy:manual/page_12"}},
				{"text": "2##","hover_event": {"action": "show_text","value": [{"text": ""},[{"text": "","font": "simplenergy:manual","color": "white"},"\"F\n","\"",{"text": "$×Çú"},{"text": "$×Çú"},{"text": "$×Çú"},"\n","\"",{"text": "U$"},{"text": "U$"},{"text": "U$"},"\n","\"",{"text": "$×Çú"},{"text": "$×Çú"},{"text": "$×Çú"},"\"\"",{"text": "$$×Çí"},"\n","\"",{"text": "U$"},{"text": "U$"},{"text": "U$"},"\"\"",{"text": "U$"},"\n","\"",{"text": "$×Çú"},{"text": "$×Çú"},{"text": "$×Çú"},"\n","\"",{"text": "U$"},{"text": "U$"},{"text": "U$"},"\n"],{"text": "\n- x9 ","color": "gray"},{"translate": "simplenergy.simplunium_nugget","color": "gray"}]},"click_event": {"action": "show_dialog","dialog": "simplenergy:manual/page_9"}},
				{"text": "2##","hover_event": {"action": "show_text","value": [{"text": ""},[{"text": "","font": "simplenergy:manual","color": "white"},"\"G\n","\"",{"text": "$×ÇÑ"},"\n","\"",{"text": "U$"},"\n","\"\"\"\"U$U$",{"text": "$$×Çí"},"\n","\"\"\"\"U$U$",{"text": "U$"},"\n","\n\n"],{"translate": "simplenergy.smelting","color": "yellow"},{"text": "\n- x1 ","color": "gray"},{"translate": "simplenergy.raw_simplunium","color": "gray"}]},"click_event": {"action": "show_dialog","dialog": "simplenergy:manual/page_10"}},
				{"text": "2##","hover_event": {"action": "show_text","value": [{"text": ""},[{"text": "","font": "simplenergy:manual","color": "white"},"\"G\n","\"",{"text": "$×Çğ"},"\n","\"",{"text": "U$"},"\n","\"\"\"\"U$U$",{"text": "$$×Çí"},"\n","\"\"\"\"U$U$",{"text": "U$"},"\n","\n\n"],{"translate": "simplenergy.smelting","color": "yellow"},{"text": "\n- x1 ","color": "gray"},{"translate": "simplenergy.simplunium_dust","color": "gray"}]},"click_event": {"action": "show_dialog","dialog": "simplenergy:manual/page_11"}},
				{"text": "2##","hover_event": {"action": "show_text","value": [{"text": ""},[{"text": "","font": "simplenergy:manual","color": "white"},"\"G\n","\"",{"text": "$×Ç½"},"\n","\"",{"text": "U$"},"\n","\"\"\"\"U$U$",{"text": "$$×Çí"},"\n","\"\"\"\"U$U$",{"text": "U$"},"\n","\n\n"],{"translate": "simplenergy.smelting","color": "yellow"},{"text": "\n- x1 ","color": "gray"},{"translate": "simplenergy.simplunium_ore","color": "gray"}]},"click_event": {"action": "show_dialog","dialog": "simplenergy:manual/page_13"}},
				{"text": "2\n","hover_event": {"action": "show_text","value": [{"text": ""},[{"text": "","font": "simplenergy:manual","color": "white"},"\"G\n","\"",{"text": "$×Ç¡"},"\n","\"",{"text": "U$"},"\n","\"\"\"\"U$U$",{"text": "$$×Çí"},"\n","\"\"\"\"U$U$",{"text": "U$"},"\n","\n\n"],{"translate": "simplenergy.smelting","color": "yellow"},{"text": "\n- x1 ","color": "gray"},{"translate": "simplenergy.deepslate_simplunium_ore","color": "gray"}]},"click_event": {"action": "show_dialog","dialog": "simplenergy:manual/page_14"}},
				{"text": "0##","hover_event": {"action": "show_text","value": [{"text": ""},[{"text": "","font": "simplenergy:manual","color": "white"},"\"E\n","\"",{"text": "$×Ç®"},"\n","\"",{"text": "U$"},"U$U$",{"text": "$$×éÅ"},"\n\"","U$U$U$",{"text": "U$"},"\n","\n"],{"text": "\n- x1 ","color": "gray"},{"translate": "simplenergy.simplunium_block","color": "gray"}]},"click_event": {"action": "show_dialog","dialog": "simplenergy:manual/page_12"}},
				{"text": "0##","hover_event": {"action": "show_text","value": [{"text": ""},[{"text": "","font": "simplenergy:manual","color": "white"},"\"F\n","\"",{"text": "$×Çú"},{"text": "$×Çú"},{"text": "$×Çú"},"\n","\"",{"text": "U$"},{"text": "U$"},{"text": "U$"},"\n","\"",{"text": "$×Çú"},{"text": "$×Çú"},{"text": "$×Çú"},"\"\"",{"text": "$$×Çí"},"\n","\"",{"text": "U$"},{"text": "U$"},{"text": "U$"},"\"\"",{"text": "U$"},"\n","\"",{"text": "$×Çú"},{"text": "$×Çú"},{"text": "$×Çú"},"\n","\"",{"text": "U$"},{"text": "U$"},{"text": "U$"},"\n"],{"text": "\n- x9 ","color": "gray"},{"translate": "simplenergy.simplunium_nugget","color": "gray"}]},"click_event": {"action": "show_dialog","dialog": "simplenergy:manual/page_9"}},
				{"text": "0##","hover_event": {"action": "show_text","value": [{"text": ""},[{"text": "","font": "simplenergy:manual","color": "white"},"\"G\n","\"",{"text": "$×ÇÑ"},"\n","\"",{"text": "U$"},"\n","\"\"\"\"U$U$",{"text": "$$×Çí"},"\n","\"\"\"\"U$U$",{"text": "U$"},"\n","\n\n"],{"translate": "simplenergy.smelting","color": "yellow"},{"text": "\n- x1 ","color": "gray"},{"translate": "simplenergy.raw_simplunium","color": "gray"}]},"click_event": {"action": "show_dialog","dialog": "simplenergy:manual/page_10"}},
				{"text": "0##","hover_event": {"action": "show_text","value": [{"text": ""},[{"text": "","font": "simplenergy:manual","color": "white"},"\"G\n","\"",{"text": "$×Çğ"},"\n","\"",{"text": "U$"},"\n","\"\"\"\"U$U$",{"text": "$$×Çí"},"\n","\"\"\"\"U$U$",{"text": "U$"},"\n","\n\n"],{"translate": "simplenergy.smelting","color": "yellow"},{"text": "\n- x1 ","color": "gray"},{"translate": "simplenergy.simplunium_dust","color": "gray"}]},"click_event": {"action": "show_dialog","dialog": "simplenergy:manual/page_11"}},
				{"text": "0##","hover_event": {"action": "show_text","value": [{"text": ""},[{"text": "","font": "simplenergy:manual","color": "white"},"\"G\n","\"",{"text": "$×Ç½"},"\n","\"",{"text": "U$"},"\n","\"\"\"\"U$U$",{"text": "$$×Çí"},"\n","\"\"\"\"U$U$",{"text": "U$"},"\n","\n\n"],{"translate": "simplenergy.smelting","color": "yellow"},{"text": "\n- x1 ","color": "gray"},{"translate": "simplenergy.simplunium_ore","color": "gray"}]},"click_event": {"action": "show_dialog","dialog": "simplenergy:manual/page_13"}},
				{"text": "0\n","hover_event": {"action": "show_text","value": [{"text": ""},[{"text": "","font": "simplenergy:manual","color": "white"},"\"G\n","\"",{"text": "$×Ç¡"},"\n","\"",{"text": "U$"},"\n","\"\"\"\"U$U$",{"text": "$$×Çí"},"\n","\"\"\"\"U$U$",{"text": "U$"},"\n","\n\n"],{"translate": "simplenergy.smelting","color": "yellow"},{"text": "\n- x1 ","color": "gray"},{"translate": "simplenergy.deepslate_simplunium_ore","color": "gray"}]},"click_event": {"action": "show_dialog","dialog": "simplenergy:manual/page_14"}},
				{"text": "×éş##","hover_event": {"action": "show_text","value": [{"text": ""},[{"text": "","font": "simplenergy:manual","color": "white"},"\"E\n","\"",{"text": "$×Çí"},"\n","\"",{"text": "U$"},"U$U$",{"text": "$$×éØ"},"\n\"","U$U$U$",{"text": "U$"},"\n","\n"],{"text": "\n- x1 ","color": "gray"},{"translate": "simplenergy.simplunium_ingot","color": "gray"}]},"click_event": {"action": "show_dialog","dialog": "simplenergy:manual/page_9"}},
				{"text": "×éó##","hover_event": {"action": "show_text","value": [{"text": ""},[{"text": "","font": "simplenergy:manual","color": "white"},"\"I\n","\n\n","\"",{"text": "$×Çí"},"\"\"\"\"#U$",{"text": "$$×Çğ"},"\n","\"",{"text": "U$"},"\"\"\"\"#U$",{"text": "U$"},"\n","\n"],{"translate": "simplenergy_pulverizing","color": "yellow"},{"text": "\n- x1 ","color": "gray"},{"translate": "simplenergy.simplunium_ingot","color": "gray"}]},"click_event": {"action": "show_dialog","dialog": "simplenergy:manual/page_11"}},
				{"text": "×éÑ##","hover_event": {"action": "show_text","value": [{"text": ""},[{"text": "","font": "simplenergy:manual","color": "white"},"\"F\n","\"",{"text": "$×Çí"},{"text": "$×Çí"},{"text": "$×Çí"},"\n","\"",{"text": "U$"},{"text": "U$"},{"text": "U$"},"\n","\"",{"text": "$×Çí"},{"text": "$×Çí"},{"text": "$×Çí"},"\"\"",{"text": "$$×Ç®"},"\n","\"",{"text": "U$"},{"text": "U$"},{"text": "U$"},"\"\"",{"text": "U$"},"\n","\"",{"text": "$×Çí"},{"text": "$×Çí"},{"text": "$×Çí"},"\n","\"",{"text": "U$"},{"text": "U$"},{"text": "U$"},"\n"],{"text": "\n- x9 ","color": "gray"},{"translate": "simplenergy.simplunium_ingot","color": "gray"}]},"click_event": {"action": "show_dialog","dialog": "simplenergy:manual/page_12"}},
				{"text": "×é¿##","hover_event": {"action": "show_text","value": [{"text": ""},[{"text": "","font": "simplenergy:manual","color": "white"},"\"F\n","\"",{"text": "$×Çí"},{"text": "$×Çí"},{"text": "$×Çí"},"\n","\"",{"text": "U$"},{"text": "U$"},{"text": "U$"},"\n","\"",{"text": "$×Çí"},"U$",{"text": "$×Çí"},"\"\"",{"text": "$$×üà"},"\n","\"",{"text": "U$"},"U$",{"text": "U$"},"\"\"",{"text": "U$"},"\n","\n\n"],{"text": "\n- x5 ","color": "gray"},{"translate": "simplenergy.simplunium_ingot","color": "gray"}]},"priority": 0,"click_event": {"action": "show_dialog","dialog": "simplenergy:manual/page_26"}},
				{"text": "×é½##","hover_event": {"action": "show_text","value": [{"text": ""},[{"text": "","font": "simplenergy:manual","color": "white"},"\"F\n","\"",{"text": "$×Çí"},"U$",{"text": "$×Çí"},"\n","\"",{"text": "U$"},"U$",{"text": "U$"},"\n","\"",{"text": "$×Çí"},{"text": "$×Çí"},{"text": "$×Çí"},"\"\"",{"text": "$$×üç"},"\n","\"",{"text": "U$"},{"text": "U$"},{"text": "U$"},"\"\"",{"text": "U$"},"\n","\"",{"text": "$×Çí"},{"text": "$×Çí"},{"text": "$×Çí"},"\n","\"",{"text": "U$"},{"text": "U$"},{"text": "U$"},"\n"],{"text": "\n- x8 ","color": "gray"},{"translate": "simplenergy.simplunium_ingot","color": "gray"}]},"priority": 0,"click_event": {"action": "show_dialog","dialog": "simplenergy:manual/page_27"}},
				{"text": "×é«\n","hover_event": {"action": "show_text","value": [{"text": ""},[{"text": "","font": "simplenergy:manual","color": "white"},"\"F\n","\"",{"text": "$×Çí"},{"text": "$×Çí"},{"text": "$×Çí"},"\n","\"",{"text": "U$"},{"text": "U$"},{"text": "U$"},"\n","\"",{"text": "$×Çí"},"U$",{"text": "$×Çí"},"\"\"",{"text": "$$×üë"},"\n","\"",{"text": "U$"},"U$",{"text": "U$"},"\"\"",{"text": "U$"},"\n","\"",{"text": "$×Çí"},"U$",{"text": "$×Çí"},"\n","\"",{"text": "U$"},"U$",{"text": "U$"},"\n"],{"text": "\n- x7 ","color": "gray"},{"translate": "simplenergy.simplunium_ingot","color": "gray"}]},"priority": 0,"click_event": {"action": "show_dialog","dialog": "simplenergy:manual/page_28"}},
				{"text": "0##","hover_event": {"action": "show_text","value": [{"text": ""},[{"text": "","font": "simplenergy:manual","color": "white"},"\"E\n","\"",{"text": "$×Çí"},"\n","\"",{"text": "U$"},"U$U$",{"text": "$$×éØ"},"\n\"","U$U$U$",{"text": "U$"},"\n","\n"],{"text": "\n- x1 ","color": "gray"},{"translate": "simplenergy.simplunium_ingot","color": "gray"}]},"click_event": {"action": "show_dialog","dialog": "simplenergy:manual/page_9"}},
				{"text": "0##","hover_event": {"action": "show_text","value": [{"text": ""},[{"text": "","font": "simplenergy:manual","color": "white"},"\"I\n","\n\n","\"",{"text": "$×Çí"},"\"\"\"\"#U$",{"text": "$$×Çğ"},"\n","\"",{"text": "U$"},"\"\"\"\"#U$",{"text": "U$"},"\n","\n"],{"translate": "simplenergy_pulverizing","color": "yellow"},{"text": "\n- x1 ","color": "gray"},{"translate": "simplenergy.simplunium_ingot","color": "gray"}]},"click_event": {"action": "show_dialog","dialog": "simplenergy:manual/page_11"}},
				{"text": "0##","hover_event": {"action": "show_text","value": [{"text": ""},[{"text": "","font": "simplenergy:manual","color": "white"},"\"F\n","\"",{"text": "$×Çí"},{"text": "$×Çí"},{"text": "$×Çí"},"\n","\"",{"text": "U$"},{"text": "U$"},{"text": "U$"},"\n","\"",{"text": "$×Çí"},{"text": "$×Çí"},{"text": "$×Çí"},"\"\"",{"text": "$$×Ç®"},"\n","\"",{"text": "U$"},{"text": "U$"},{"text": "U$"},"\"\"",{"text": "U$"},"\n","\"",{"text": "$×Çí"},{"text": "$×Çí"},{"text": "$×Çí"},"\n","\"",{"text": "U$"},{"text": "U$"},{"text": "U$"},"\n"],{"text": "\n- x9 ","color": "gray"},{"translate": "simplenergy.simplunium_ingot","color": "gray"}]},"click_event": {"action": "show_dialog","dialog": "simplenergy:manual/page_12"}},
				{"text": "0##","hover_event": {"action": "show_text","value": [{"text": ""},[{"text": "","font": "simplenergy:manual","color": "white"},"\"F\n","\"",{"text": "$×Çí"},{"text": "$×Çí"},{"text": "$×Çí"},"\n","\"",{"text": "U$"},{"text": "U$"},{"text": "U$"},"\n","\"",{"text": "$×Çí"},"U$",{"text": "$×Çí"},"\"\"",{"text": "$$×üà"},"\n","\"",{"text": "U$"},"U$",{"text": "U$"},"\"\"",{"text": "U$"},"\n","\n\n"],{"text": "\n- x5 ","color": "gray"},{"translate": "simplenergy.simplunium_ingot","color": "gray"}]},"priority": 0,"click_event": {"action": "show_dialog","dialog": "simplenergy:manual/page_26"}},
				{"text": "0##","hover_event": {"action": "show_text","value": [{"text": ""},[{"text": "","font": "simplenergy:manual","color": "white"},"\"F\n","\"",{"text": "$×Çí"},"U$",{"text": "$×Çí"},"\n","\"",{"text": "U$"},"U$",{"text": "U$"},"\n","\"",{"text": "$×Çí"},{"text": "$×Çí"},{"text": "$×Çí"},"\"\"",{"text": "$$×üç"},"\n","\"",{"text": "U$"},{"text": "U$"},{"text": "U$"},"\"\"",{"text": "U$"},"\n","\"",{"text": "$×Çí"},{"text": "$×Çí"},{"text": "$×Çí"},"\n","\"",{"text": "U$"},{"text": "U$"},{"text": "U$"},"\n"],{"text": "\n- x8 ","color": "gray"},{"translate": "simplenergy.simplunium_ingot","color": "gray"}]},"priority": 0,"click_event": {"action": "show_dialog","dialog": "simplenergy:manual/page_27"}},
				{"text": "0\n","hover_event": {"action": "show_text","value": [{"text": ""},[{"text": "","font": "simplenergy:manual","color": "white"},"\"F\n","\"",{"text": "$×Çí"},{"text": "$×Çí"},{"text": "$×Çí"},"\n","\"",{"text": "U$"},{"text": "U$"},{"text": "U$"},"\n","\"",{"text": "$×Çí"},"U$",{"text": "$×Çí"},"\"\"",{"text": "$$×üë"},"\n","\"",{"text": "U$"},"U$",{"text": "U$"},"\"\"",{"text": "U$"},"\n","\"",{"text": "$×Çí"},"U$",{"text": "$×Çí"},"\n","\"",{"text": "U$"},"U$",{"text": "U$"},"\n"],{"text": "\n- x7 ","color": "gray"},{"translate": "simplenergy.simplunium_ingot","color": "gray"}]},"priority": 0,"click_event": {"action": "show_dialog","dialog": "simplenergy:manual/page_28"}},
				{"text": "×é▒##","hover_event": {"action": "show_text","value": [{"text": ""},[{"text": "","font": "simplenergy:manual","color": "white"},"\"F\n","\"",{"text": "$×Çí"},"U$",{"text": "$×Çí"},"\n","\"",{"text": "U$"},"U$",{"text": "U$"},"\n","\"",{"text": "$×Çí"},"U$",{"text": "$×Çí"},"\"\"",{"text": "$$×üï"},"\n","\"",{"text": "U$"},"U$",{"text": "U$"},"\"\"",{"text": "U$"},"\n","\n\n"],{"text": "\n- x4 ","color": "gray"},{"translate": "simplenergy.simplunium_ingot","color": "gray"}]},"priority": 0,"click_event": {"action": "show_dialog","dialog": "simplenergy:manual/page_29"}},
				{"text": "×éÁ##","hover_event": {"action": "show_text","value": [{"text": ""},[{"text": "","font": "simplenergy:manual","color": "white"},"\"F\n","\"","U$",{"text": "$×Çí"},"U$","\n","\"","U$",{"text": "U$"},"U$","\n","\"","U$",{"text": "$×Çí"},"U$","\"\"",{"text": "$$×üı"},"\n","\"","U$",{"text": "U$"},"U$","\"\"",{"text": "U$"},"\n","\"","U$",{"text": "$×é┤"},"U$","\n","\"","U$",{"text": "U$"},"U$","\n"],{"text": "\n- x2 ","color": "gray"},{"translate": "simplenergy.simplunium_ingot","color": "gray"},{"text": "\n- x1 ","color": "gray"},{"translate": "simplenergy.stick","color": "gray"}]},"priority": 0,"click_event": {"action": "show_dialog","dialog": "simplenergy:manual/page_30"}},
				{"text": "×é╣##","hover_event": {"action": "show_text","value": [{"text": ""},[{"text": "","font": "simplenergy:manual","color": "white"},"\"F\n","\"",{"text": "$×Çí"},{"text": "$×Çí"},{"text": "$×Çí"},"\n","\"",{"text": "U$"},{"text": "U$"},{"text": "U$"},"\n","\"","U$",{"text": "$×é┤"},"U$","\"\"",{"text": "$$×üÅ"},"\n","\"","U$",{"text": "U$"},"U$","\"\"",{"text": "U$"},"\n","\"","U$",{"text": "$×é┤"},"U$","\n","\"","U$",{"text": "U$"},"U$","\n"],{"text": "\n- x3 ","color": "gray"},{"translate": "simplenergy.simplunium_ingot","color": "gray"},{"text": "\n- x2 ","color": "gray"},{"translate": "simplenergy.stick","color": "gray"}]},"priority": 0,"click_event": {"action": "show_dialog","dialog": "simplenergy:manual/page_31"}},
				{"text": "×é¢##","hover_event": {"action": "show_text","value": [{"text": ""},[{"text": "","font": "simplenergy:manual","color": "white"},"\"F\n","\"",{"text": "$×Çí"},{"text": "$×Çí"},"\n","\"",{"text": "U$"},{"text": "U$"},"\n","\"",{"text": "$×Çí"},{"text": "$×é┤"},"U$\"\"",{"text": "$$×üæ"},"\n","\"",{"text": "U$"},{"text": "U$"},"U$\"\"",{"text": "U$"},"\n","\"","U$",{"text": "$×é┤"},"\n","\"","U$",{"text": "U$"},"\n"],{"text": "\n- x3 ","color": "gray"},{"translate": "simplenergy.simplunium_ingot","color": "gray"},{"text": "\n- x2 ","color": "gray"},{"translate": "simplenergy.stick","color": "gray"}]},"priority": 0,"click_event": {"action": "show_dialog","dialog": "simplenergy:manual/page_32"}},
				{"text": "×âü##","hover_event": {"action": "show_text","value": [{"text": ""},[{"text": "","font": "simplenergy:manual","color": "white"},"\"F\n","\"","U$",{"text": "$×Çí"},"U$","\n","\"","U$",{"text": "U$"},"U$","\n","\"","U$",{"text": "$×é┤"},"U$","\"\"",{"text": "$$×üô"},"\n","\"","U$",{"text": "U$"},"U$","\"\"",{"text": "U$"},"\n","\"","U$",{"text": "$×é┤"},"U$","\n","\"","U$",{"text": "U$"},"U$","\n"],{"text": "\n- x1 ","color": "gray"},{"translate": "simplenergy.simplunium_ingot","color": "gray"},{"text": "\n- x2 ","color": "gray"},{"translate": "simplenergy.stick","color": "gray"}]},"priority": 0,"click_event": {"action": "show_dialog","dialog": "simplenergy:manual/page_33"}},
				{"text": "×âà\n","hover_event": {"action": "show_text","value": [{"text": ""},[{"text": "","font": "simplenergy:manual","color": "white"},"\"F\n","\"",{"text": "$×Çí"},{"text": "$×Çí"},"\n","\"",{"text": "U$"},{"text": "U$"},"\n","\"","U$",{"text": "$×é┤"},"U$\"\"",{"text": "$$×üò"},"\n","\"","U$",{"text": "U$"},"U$\"\"",{"text": "U$"},"\n","\"","U$",{"text": "$×é┤"},"\n","\"","U$",{"text": "U$"},"\n"],{"text": "\n- x2 ","color": "gray"},{"translate": "simplenergy.simplunium_ingot","color": "gray"},{"text": "\n- x2 ","color": "gray"},{"translate": "simplenergy.stick","color": "gray"}]},"priority": 0,"click_event": {"action": "show_dialog","dialog": "simplenergy:manual/page_34"}},
				{"text": "0##","hover_event": {"action": "show_text","value": [{"text": ""},[{"text": "","font": "simplenergy:manual","color": "white"},"\"F\n","\"",{"text": "$×Çí"},"U$",{"text": "$×Çí"},"\n","\"",{"text": "U$"},"U$",{"text": "U$"},"\n","\"",{"text": "$×Çí"},"U$",{"text": "$×Çí"},"\"\"",{"text": "$$×üï"},"\n","\"",{"text": "U$"},"U$",{"text": "U$"},"\"\"",{"text": "U$"},"\n","\n\n"],{"text": "\n- x4 ","color": "gray"},{"translate": "simplenergy.simplunium_ingot","color": "gray"}]},"priority": 0,"click_event": {"action": "show_dialog","dialog": "simplenergy:manual/page_29"}},
				{"text": "0##","hover_event": {"action": "show_text","value": [{"text": ""},[{"text": "","font": "simplenergy:manual","color": "white"},"\"F\n","\"","U$",{"text": "$×Çí"},"U$","\n","\"","U$",{"text": "U$"},"U$","\n","\"","U$",{"text": "$×Çí"},"U$","\"\"",{"text": "$$×üı"},"\n","\"","U$",{"text": "U$"},"U$","\"\"",{"text": "U$"},"\n","\"","U$",{"text": "$×é┤"},"U$","\n","\"","U$",{"text": "U$"},"U$","\n"],{"text": "\n- x2 ","color": "gray"},{"translate": "simplenergy.simplunium_ingot","color": "gray"},{"text": "\n- x1 ","color": "gray"},{"translate": "simplenergy.stick","color": "gray"}]},"priority": 0,"click_event": {"action": "show_dialog","dialog": "simplenergy:manual/page_30"}},
				{"text": "0##","hover_event": {"action": "show_text","value": [{"text": ""},[{"text": "","font": "simplenergy:manual","color": "white"},"\"F\n","\"",{"text": "$×Çí"},{"text": "$×Çí"},{"text": "$×Çí"},"\n","\"",{"text": "U$"},{"text": "U$"},{"text": "U$"},"\n","\"","U$",{"text": "$×é┤"},"U$","\"\"",{"text": "$$×üÅ"},"\n","\"","U$",{"text": "U$"},"U$","\"\"",{"text": "U$"},"\n","\"","U$",{"text": "$×é┤"},"U$","\n","\"","U$",{"text": "U$"},"U$","\n"],{"text": "\n- x3 ","color": "gray"},{"translate": "simplenergy.simplunium_ingot","color": "gray"},{"text": "\n- x2 ","color": "gray"},{"translate": "simplenergy.stick","color": "gray"}]},"priority": 0,"click_event": {"action": "show_dialog","dialog": "simplenergy:manual/page_31"}},
				{"text": "0##","hover_event": {"action": "show_text","value": [{"text": ""},[{"text": "","font": "simplenergy:manual","color": "white"},"\"F\n","\"",{"text": "$×Çí"},{"text": "$×Çí"},"\n","\"",{"text": "U$"},{"text": "U$"},"\n","\"",{"text": "$×Çí"},{"text": "$×é┤"},"U$\"\"",{"text": "$$×üæ"},"\n","\"",{"text": "U$"},{"text": "U$"},"U$\"\"",{"text": "U$"},"\n","\"","U$",{"text": "$×é┤"},"\n","\"","U$",{"text": "U$"},"\n"],{"text": "\n- x3 ","color": "gray"},{"translate": "simplenergy.simplunium_ingot","color": "gray"},{"text": "\n- x2 ","color": "gray"},{"translate": "simplenergy.stick","color": "gray"}]},"priority": 0,"click_event": {"action": "show_dialog","dialog": "simplenergy:manual/page_32"}},
				{"text": "0##","hover_event": {"action": "show_text","value": [{"text": ""},[{"text": "","font": "simplenergy:manual","color": "white"},"\"F\n","\"","U$",{"text": "$×Çí"},"U$","\n","\"","U$",{"text": "U$"},"U$","\n","\"","U$",{"text": "$×é┤"},"U$","\"\"",{"text": "$$×üô"},"\n","\"","U$",{"text": "U$"},"U$","\"\"",{"text": "U$"},"\n","\"","U$",{"text": "$×é┤"},"U$","\n","\"","U$",{"text": "U$"},"U$","\n"],{"text": "\n- x1 ","color": "gray"},{"translate": "simplenergy.simplunium_ingot","color": "gray"},{"text": "\n- x2 ","color": "gray"},{"translate": "simplenergy.stick","color": "gray"}]},"priority": 0,"click_event": {"action": "show_dialog","dialog": "simplenergy:manual/page_33"}},
				{"text": "0\n","hover_event": {"action": "show_text","value": [{"text": ""},[{"text": "","font": "simplenergy:manual","color": "white"},"\"F\n","\"",{"text": "$×Çí"},{"text": "$×Çí"},"\n","\"",{"text": "U$"},{"text": "U$"},"\n","\"","U$",{"text": "$×é┤"},"U$\"\"",{"text": "$$×üò"},"\n","\"","U$",{"text": "U$"},"U$\"\"",{"text": "U$"},"\n","\"","U$",{"text": "$×é┤"},"\n","\"","U$",{"text": "U$"},"\n"],{"text": "\n- x2 ","color": "gray"},{"translate": "simplenergy.simplunium_ingot","color": "gray"},{"text": "\n- x2 ","color": "gray"},{"translate": "simplenergy.stick","color": "gray"}]},"priority": 0,"click_event": {"action": "show_dialog","dialog": "simplenergy:manual/page_34"}},
				{"text": "×âë##","hover_event": {"action": "show_text","value": [{"text": ""},[{"text": "","font": "simplenergy:manual","color": "white"},"\"F\n","\"","U$","U$",{"text": "$×Çí"},"\n","\"","U$","U$",{"text": "U$"},"\n","\"","U$",{"text": "$×Çí"},"U$","\"\"",{"text": "$$×üù"},"\n","\"","U$",{"text": "U$"},"U$","\"\"",{"text": "U$"},"\n","\"",{"text": "$×é┤"},"U$","U$","\n","\"",{"text": "U$"},"U$","U$","\n"],{"text": "\n- x2 ","color": "gray"},{"translate": "simplenergy.simplunium_ingot","color": "gray"},{"text": "\n- x1 ","color": "gray"},{"translate": "simplenergy.stick","color": "gray"}]},"priority": 0,"click_event": {"action": "show_dialog","dialog": "simplenergy:manual/page_35"}},
				{"text": "×âî##","hover_event": {"action": "show_text","value": [{"text": ""},[{"text": "","font": "simplenergy:manual","color": "white"},"\"F\n","\"","U$",{"text": "$×Çí"},"U$","\n","\"","U$",{"text": "U$"},"U$","\n","\"","U$",{"text": "$×Çí"},{"text": "$×Çí"},"\"\"",{"text": "$$×üØ"},"\n","\"","U$",{"text": "U$"},{"text": "U$"},"\"\"",{"text": "U$"},"\n","\"",{"text": "$×Çí"},"U$","U$","\n","\"",{"text": "U$"},"U$","U$","\n"],{"text": "\n- x4 ","color": "gray"},{"translate": "simplenergy.simplunium_ingot","color": "gray"}]},"click_event": {"action": "show_dialog","dialog": "simplenergy:manual/page_38"}},
				{"text": "×âæ##","hover_event": {"action": "show_text","value": [{"text": ""},[{"text": "","font": "simplenergy:manual","color": "white"},"\"F\n","\"","U$",{"text": "$×âÄ"},{"text": "$×Çí"},"\n","\"","U$",{"text": "U$"},{"text": "U$"},"\n","\"","U$",{"text": "$×Çí"},{"text": "$×âÉ"},"\"\"",{"text": "$$×üí"},"\n","\"","U$",{"text": "U$"},{"text": "U$"},"\"\"",{"text": "U$"},"\n","\"",{"text": "$×Çí"},"U$","U$","\n","\"",{"text": "U$"},"U$","U$","\n"],{"text": "\n- x1 ","color": "gray"},{"translate": "simplenergy.redstone","color": "gray"},{"text": "\n- x3 ","color": "gray"},{"translate": "simplenergy.simplunium_ingot","color": "gray"},{"text": "\n- x1 ","color": "gray"},{"translate": "simplenergy.stone_button","color": "gray"}]},"click_event": {"action": "show_dialog","dialog": "simplenergy:manual/page_40"}},
				{"text": "×âû##","hover_event": {"action": "show_text","value": [{"text": ""},[{"text": "","font": "simplenergy:manual","color": "white"},"\"F\n","\"",{"text": "$×Çí"},{"text": "$×Çí"},{"text": "$×Çí"},"\n","\"",{"text": "U$"},{"text": "U$"},{"text": "U$"},"\n","\"",{"text": "$×Çí"},{"text": "$×ü╣"},{"text": "$×Çí"},"\"\"",{"text": "$$×ü╗"},"\n","\"",{"text": "U$"},{"text": "U$"},{"text": "U$"},"\"\"",{"text": "U$"},"\n","\"",{"text": "$×Ç®"},{"text": "$×Ç®"},{"text": "$×Ç®"},"\n","\"",{"text": "U$"},{"text": "U$"},{"text": "U$"},"\n"],{"text": "\n- x5 ","color": "gray"},{"translate": "simplenergy.simplunium_ingot","color": "gray"},{"text": "\n- x1 ","color": "gray"},{"translate": "simplenergy.electric_furnace","color": "gray"},{"text": "\n- x3 ","color": "gray"},{"translate": "simplenergy.simplunium_block","color": "gray"}]},"click_event": {"action": "show_dialog","dialog": "simplenergy:manual/page_53"}},
				{"text": "×âø##","hover_event": {"action": "show_text","value": [{"text": ""},[{"text": "","font": "simplenergy:manual","color": "white"},"\"F\n","\"",{"text": "$×Çí"},{"text": "$×Çí"},{"text": "$×Çí"},"\n","\"",{"text": "U$"},{"text": "U$"},{"text": "U$"},"\n","\"",{"text": "$×Çí"},{"text": "$×âÖ"},{"text": "$×Çí"},"\"\"",{"text": "$$×ü¢"},"\n","\"",{"text": "U$"},{"text": "U$"},{"text": "U$"},"\"\"",{"text": "U$"},"\n","\"",{"text": "$×âÜ"},{"text": "$×âÜ"},{"text": "$×âÜ"},"\n","\"",{"text": "U$"},{"text": "U$"},{"text": "U$"},"\n"],{"text": "\n- x5 ","color": "gray"},{"translate": "simplenergy.simplunium_ingot","color": "gray"},{"text": "\n- x1 ","color": "gray"},{"translate": "simplenergy.brewing_stand","color": "gray"},{"text": "\n- x3 ","color": "gray"},{"translate": "simplenergy.lapis_block","color": "gray"}]},"click_event": {"action": "show_dialog","dialog": "simplenergy:manual/page_54"}},
				{"text": "×âí\n","hover_event": {"action": "show_text","value": [{"text": ""},[{"text": "","font": "simplenergy:manual","color": "white"},"\"F\n","\"",{"text": "$×âØ"},{"text": "$×âØ"},{"text": "$×âØ"},"\n","\"",{"text": "U$"},{"text": "U$"},{"text": "U$"},"\n","\"",{"text": "$×Çí"},{"text": "$×üÑ"},{"text": "$×Çí"},"\"\"",{"text": "$$×ü┐"},"\n","\"",{"text": "U$"},{"text": "U$"},{"text": "U$"},"\"\"",{"text": "U$"},"\n","\"",{"text": "$×âá"},{"text": "$×âá"},{"text": "$×âá"},"\n","\"",{"text": "U$"},{"text": "U$"},{"text": "U$"},"\n"],{"text": "\n- x3 ","color": "gray"},{"translate": "simplenergy.diamond","color": "gray"},{"text": "\n- x2 ","color": "gray"},{"translate": "simplenergy.simplunium_ingot","color": "gray"},{"text": "\n- x1 ","color": "gray"},{"translate": "simplenergy.machine_block","color": "gray"},{"text": "\n- x3 ","color": "gray"},{"translate": "simplenergy.iron_block","color": "gray"}]},"click_event": {"action": "show_dialog","dialog": "simplenergy:manual/page_55"}},
				{"text": "0##","hover_event": {"action": "show_text","value": [{"text": ""},[{"text": "","font": "simplenergy:manual","color": "white"},"\"F\n","\"","U$","U$",{"text": "$×Çí"},"\n","\"","U$","U$",{"text": "U$"},"\n","\"","U$",{"text": "$×Çí"},"U$","\"\"",{"text": "$$×üù"},"\n","\"","U$",{"text": "U$"},"U$","\"\"",{"text": "U$"},"\n","\"",{"text": "$×é┤"},"U$","U$","\n","\"",{"text": "U$"},"U$","U$","\n"],{"text": "\n- x2 ","color": "gray"},{"translate": "simplenergy.simplunium_ingot","color": "gray"},{"text": "\n- x1 ","color": "gray"},{"translate": "simplenergy.stick","color": "gray"}]},"priority": 0,"click_event": {"action": "show_dialog","dialog": "simplenergy:manual/page_35"}},
				{"text": "0##","hover_event": {"action": "show_text","value": [{"text": ""},[{"text": "","font": "simplenergy:manual","color": "white"},"\"F\n","\"","U$",{"text": "$×Çí"},"U$","\n","\"","U$",{"text": "U$"},"U$","\n","\"","U$",{"text": "$×Çí"},{"text": "$×Çí"},"\"\"",{"text": "$$×üØ"},"\n","\"","U$",{"text": "U$"},{"text": "U$"},"\"\"",{"text": "U$"},"\n","\"",{"text": "$×Çí"},"U$","U$","\n","\"",{"text": "U$"},"U$","U$","\n"],{"text": "\n- x4 ","color": "gray"},{"translate": "simplenergy.simplunium_ingot","color": "gray"}]},"click_event": {"action": "show_dialog","dialog": "simplenergy:manual/page_38"}},
				{"text": "0##","hover_event": {"action": "show_text","value": [{"text": ""},[{"text": "","font": "simplenergy:manual","color": "white"},"\"F\n","\"","U$",{"text": "$×âÄ"},{"text": "$×Çí"},"\n","\"","U$",{"text": "U$"},{"text": "U$"},"\n","\"","U$",{"text": "$×Çí"},{"text": "$×âÉ"},"\"\"",{"text": "$$×üí"},"\n","\"","U$",{"text": "U$"},{"text": "U$"},"\"\"",{"text": "U$"},"\n","\"",{"text": "$×Çí"},"U$","U$","\n","\"",{"text": "U$"},"U$","U$","\n"],{"text": "\n- x1 ","color": "gray"},{"translate": "simplenergy.redstone","color": "gray"},{"text": "\n- x3 ","color": "gray"},{"translate": "simplenergy.simplunium_ingot","color": "gray"},{"text": "\n- x1 ","color": "gray"},{"translate": "simplenergy.stone_button","color": "gray"}]},"click_event": {"action": "show_dialog","dialog": "simplenergy:manual/page_40"}},
				{"text": "0##","hover_event": {"action": "show_text","value": [{"text": ""},[{"text": "","font": "simplenergy:manual","color": "white"},"\"F\n","\"",{"text": "$×Çí"},{"text": "$×Çí"},{"text": "$×Çí"},"\n","\"",{"text": "U$"},{"text": "U$"},{"text": "U$"},"\n","\"",{"text": "$×Çí"},{"text": "$×ü╣"},{"text": "$×Çí"},"\"\"",{"text": "$$×ü╗"},"\n","\"",{"text": "U$"},{"text": "U$"},{"text": "U$"},"\"\"",{"text": "U$"},"\n","\"",{"text": "$×Ç®"},{"text": "$×Ç®"},{"text": "$×Ç®"},"\n","\"",{"text": "U$"},{"text": "U$"},{"text": "U$"},"\n"],{"text": "\n- x5 ","color": "gray"},{"translate": "simplenergy.simplunium_ingot","color": "gray"},{"text": "\n- x1 ","color": "gray"},{"translate": "simplenergy.electric_furnace","color": "gray"},{"text": "\n- x3 ","color": "gray"},{"translate": "simplenergy.simplunium_block","color": "gray"}]},"click_event": {"action": "show_dialog","dialog": "simplenergy:manual/page_53"}},
				{"text": "0##","hover_event": {"action": "show_text","value": [{"text": ""},[{"text": "","font": "simplenergy:manual","color": "white"},"\"F\n","\"",{"text": "$×Çí"},{"text": "$×Çí"},{"text": "$×Çí"},"\n","\"",{"text": "U$"},{"text": "U$"},{"text": "U$"},"\n","\"",{"text": "$×Çí"},{"text": "$×âÖ"},{"text": "$×Çí"},"\"\"",{"text": "$$×ü¢"},"\n","\"",{"text": "U$"},{"text": "U$"},{"text": "U$"},"\"\"",{"text": "U$"},"\n","\"",{"text": "$×âÜ"},{"text": "$×âÜ"},{"text": "$×âÜ"},"\n","\"",{"text": "U$"},{"text": "U$"},{"text": "U$"},"\n"],{"text": "\n- x5 ","color": "gray"},{"translate": "simplenergy.simplunium_ingot","color": "gray"},{"text": "\n- x1 ","color": "gray"},{"translate": "simplenergy.brewing_stand","color": "gray"},{"text": "\n- x3 ","color": "gray"},{"translate": "simplenergy.lapis_block","color": "gray"}]},"click_event": {"action": "show_dialog","dialog": "simplenergy:manual/page_54"}},
				{"text": "0\n","hover_event": {"action": "show_text","value": [{"text": ""},[{"text": "","font": "simplenergy:manual","color": "white"},"\"F\n","\"",{"text": "$×âØ"},{"text": "$×âØ"},{"text": "$×âØ"},"\n","\"",{"text": "U$"},{"text": "U$"},{"text": "U$"},"\n","\"",{"text": "$×Çí"},{"text": "$×üÑ"},{"text": "$×Çí"},"\"\"",{"text": "$$×ü┐"},"\n","\"",{"text": "U$"},{"text": "U$"},{"text": "U$"},"\"\"",{"text": "U$"},"\n","\"",{"text": "$×âá"},{"text": "$×âá"},{"text": "$×âá"},"\n","\"",{"text": "U$"},{"text": "U$"},{"text": "U$"},"\n"],{"text": "\n- x3 ","color": "gray"},{"translate": "simplenergy.diamond","color": "gray"},{"text": "\n- x2 ","color": "gray"},{"translate": "simplenergy.simplunium_ingot","color": "gray"},{"text": "\n- x1 ","color": "gray"},{"translate": "simplenergy.machine_block","color": "gray"},{"text": "\n- x3 ","color": "gray"},{"translate": "simplenergy.iron_block","color": "gray"}]},"click_event": {"action": "show_dialog","dialog": "simplenergy:manual/page_55"}},
				{"text": "×âÑ##","hover_event": {"action": "show_text","value": [{"text": ""},[{"text": "","font": "simplenergy:manual","color": "white"},"\"F\n","\"","U$","U$","U$","\n","\"","U$","U$","U$","\n","\"",{"text": "$×Çí"},{"text": "$×âñ"},{"text": "$×Çí"},"\"\"",{"text": "$$×âó"},"\n","\"",{"text": "U$"},{"text": "U$"},{"text": "U$"},"\"\"",{"text": "U$"},"\n","\"","U$","U$","U$","\n","\"","U$","U$","U$","\n"],{"text": "\n- x2 ","color": "gray"},{"translate": "simplenergy.simplunium_ingot","color": "gray"},{"text": "\n- x1 ","color": "gray"},{"translate": "simplenergy.glass","color": "gray"}]},"click_event": {"action": "show_dialog","dialog": "simplenergy:manual/page_60"}},
				{"text": "×â¼##","hover_event": {"action": "show_text","value": [{"text": ""},[{"text": "","font": "simplenergy:manual","color": "white"},"\"F\n","\"",{"text": "$×éë"},{"text": "$×â¿"},{"text": "$×éë"},"\n","\"",{"text": "U$"},{"text": "U$"},{"text": "U$"},"\n","\"",{"text": "$×Çí"},{"text": "$×â¬"},{"text": "$×Çí"},"\"\"",{"text": "$$×éï"},"\n","\"",{"text": "U$"},{"text": "U$"},{"text": "U$"},"\"\"",{"text": "U$"},"\n","\"","U$",{"text": "$×â½"},"U$","\n","\"","U$",{"text": "U$"},"U$","\n"],{"text": "\n- x2 ","color": "gray"},{"translate": "simplenergy.basic_item_cable","color": "gray"},{"text": "\n- x1 ","color": "gray"},{"translate": "simplenergy.redstone_block","color": "gray"},{"text": "\n- x2 ","color": "gray"},{"translate": "simplenergy.simplunium_ingot","color": "gray"},{"text": "\n- x1 ","color": "gray"},{"translate": "simplenergy.comparator","color": "gray"},{"text": "\n- x1 ","color": "gray"},{"translate": "simplenergy.emerald","color": "gray"}]},"click_event": {"action": "show_dialog","dialog": "simplenergy:manual/page_61"}},
				{"text": "×â│##","hover_event": {"action": "show_text","value": [{"text": ""},[{"text": "","font": "simplenergy:manual","color": "white"},"\"F\n","\"","U$",{"text": "$×âØ"},"U$","\n","\"","U$",{"text": "U$"},"U$","\n","\"",{"text": "$×Çí"},{"text": "$×â¬"},{"text": "$×Çí"},"\"\"",{"text": "$$×éı"},"\n","\"",{"text": "U$"},{"text": "U$"},{"text": "U$"},"\"\"",{"text": "U$"},"\n","\"",{"text": "$×éë"},{"text": "$×â¿"},{"text": "$×éë"},"\n","\"",{"text": "U$"},{"text": "U$"},{"text": "U$"},"\n"],{"text": "\n- x2 ","color": "gray"},{"translate": "simplenergy.basic_item_cable","color": "gray"},{"text": "\n- x1 ","color": "gray"},{"translate": "simplenergy.redstone_block","color": "gray"},{"text": "\n- x2 ","color": "gray"},{"translate": "simplenergy.simplunium_ingot","color": "gray"},{"text": "\n- x1 ","color": "gray"},{"translate": "simplenergy.comparator","color": "gray"},{"text": "\n- x1 ","color": "gray"},{"translate": "simplenergy.diamond","color": "gray"}]},"click_event": {"action": "show_dialog","dialog": "simplenergy:manual/page_62"}},
				{"text": "×âÀ\n","hover_event": {"action": "show_text","value": [{"text": ""},[{"text": "","font": "simplenergy:manual","color": "white"},"\"E\n","\"",{"text": "$×âÁ"},{"text": "$×Çí"},"\n","\"",{"text": "U$"},{"text": "U$"},"U$",{"text": "$$×üú"},"\n\"","U$U$U$",{"text": "U$"},"\n","\n"],{"text": "\n- x1 ","color": "gray"},{"translate": "simplenergy.book","color": "gray"},{"text": "\n- x1 ","color": "gray"},{"translate": "simplenergy.simplunium_ingot","color": "gray"}]},"click_event": {"action": "show_dialog","dialog": "simplenergy:manual/page_41"}},
				{"text": "0##","hover_event": {"action": "show_text","value": [{"text": ""},[{"text": "","font": "simplenergy:manual","color": "white"},"\"F\n","\"","U$","U$","U$","\n","\"","U$","U$","U$","\n","\"",{"text": "$×Çí"},{"text": "$×âñ"},{"text": "$×Çí"},"\"\"",{"text": "$$×âó"},"\n","\"",{"text": "U$"},{"text": "U$"},{"text": "U$"},"\"\"",{"text": "U$"},"\n","\"","U$","U$","U$","\n","\"","U$","U$","U$","\n"],{"text": "\n- x2 ","color": "gray"},{"translate": "simplenergy.simplunium_ingot","color": "gray"},{"text": "\n- x1 ","color": "gray"},{"translate": "simplenergy.glass","color": "gray"}]},"click_event": {"action": "show_dialog","dialog": "simplenergy:manual/page_60"}},
				{"text": "0##","hover_event": {"action": "show_text","value": [{"text": ""},[{"text": "","font": "simplenergy:manual","color": "white"},"\"F\n","\"",{"text": "$×éë"},{"text": "$×â¿"},{"text": "$×éë"},"\n","\"",{"text": "U$"},{"text": "U$"},{"text": "U$"},"\n","\"",{"text": "$×Çí"},{"text": "$×â¬"},{"text": "$×Çí"},"\"\"",{"text": "$$×éï"},"\n","\"",{"text": "U$"},{"text": "U$"},{"text": "U$"},"\"\"",{"text": "U$"},"\n","\"","U$",{"text": "$×â½"},"U$","\n","\"","U$",{"text": "U$"},"U$","\n"],{"text": "\n- x2 ","color": "gray"},{"translate": "simplenergy.basic_item_cable","color": "gray"},{"text": "\n- x1 ","color": "gray"},{"translate": "simplenergy.redstone_block","color": "gray"},{"text": "\n- x2 ","color": "gray"},{"translate": "simplenergy.simplunium_ingot","color": "gray"},{"text": "\n- x1 ","color": "gray"},{"translate": "simplenergy.comparator","color": "gray"},{"text": "\n- x1 ","color": "gray"},{"translate": "simplenergy.emerald","color": "gray"}]},"click_event": {"action": "show_dialog","dialog": "simplenergy:manual/page_61"}},
				{"text": "0##","hover_event": {"action": "show_text","value": [{"text": ""},[{"text": "","font": "simplenergy:manual","color": "white"},"\"F\n","\"","U$",{"text": "$×âØ"},"U$","\n","\"","U$",{"text": "U$"},"U$","\n","\"",{"text": "$×Çí"},{"text": "$×â¬"},{"text": "$×Çí"},"\"\"",{"text": "$$×éı"},"\n","\"",{"text": "U$"},{"text": "U$"},{"text": "U$"},"\"\"",{"text": "U$"},"\n","\"",{"text": "$×éë"},{"text": "$×â¿"},{"text": "$×éë"},"\n","\"",{"text": "U$"},{"text": "U$"},{"text": "U$"},"\n"],{"text": "\n- x2 ","color": "gray"},{"translate": "simplenergy.basic_item_cable","color": "gray"},{"text": "\n- x1 ","color": "gray"},{"translate": "simplenergy.redstone_block","color": "gray"},{"text": "\n- x2 ","color": "gray"},{"translate": "simplenergy.simplunium_ingot","color": "gray"},{"text": "\n- x1 ","color": "gray"},{"translate": "simplenergy.comparator","color": "gray"},{"text": "\n- x1 ","color": "gray"},{"translate": "simplenergy.diamond","color": "gray"}]},"click_event": {"action": "show_dialog","dialog": "simplenergy:manual/page_62"}},
				{"text": "0","hover_event": {"action": "show_text","value": [{"text": ""},[{"text": "","font": "simplenergy:manual","color": "white"},"\"E\n","\"",{"text": "$×âÁ"},{"text": "$×Çí"},"\n","\"",{"text": "U$"},{"text": "U$"},"U$",{"text": "$$×üú"},"\n\"","U$U$U$",{"text": "U$"},"\n","\n"],{"text": "\n- x1 ","color": "gray"},{"translate": "simplenergy.book","color": "gray"},{"text": "\n- x1 ","color": "gray"},{"translate": "simplenergy.simplunium_ingot","color": "gray"}]},"click_event": {"action": "show_dialog","dialog": "simplenergy:manual/page_41"}},
				"\n\n\n\n\n\n\n\n\n\n"
			],
			"width": 140
		}
	]
}
